chessdata/__init__.py
chessdata_pyclient-0.0.4.dist-info/METADATA
chessdata_pyclient-0.0.4.dist-info/WHEEL
chessdata_pyclient-0.0.4.dist-info/top_level.txt
chessdata_pyclient-0.0.4.dist-info/RECORD
