Metadata-Version: 2.1
Name: chessdata-pyclient
Version: 0.0.4
Summary: Python library for interacting with the CHESS metadata service
Home-page: https://github.com/CHESSComputing/chessdata-pyclient
Author: Keara Soloway
Author-email: kls286@cornell.edu
Classifier: Programming Language :: Python :: 3
Classifier: License :: OSI Approved :: MIT License
Classifier: Operating System :: OS Independent
Requires-Python: >=3.8
Requires-Dist: requests
Requires-Dist: pyjwt
